README.rst
setup.py
ggc/__init__.py
ggc/args.py
ggc/fasta.py
ggc/file.py
ggc/prompt.py
ggc.egg-info/PKG-INFO
ggc.egg-info/SOURCES.txt
ggc.egg-info/dependency_links.txt
ggc.egg-info/requires.txt
ggc.egg-info/top_level.txt