Metadata-Version: 2.1
Name: ggc
Version: 0.0.3
Summary: Basic methods, for common usage across packages
Home-page: https://github.com/ggirelli/ggc
Author: Gabriele Girelli
Author-email: gabriele.girelli@scilifelab.se
License: MIT
Keywords: common
Platform: UNKNOWN
Classifier: Development Status :: 4 - Beta
Classifier: Intended Audience :: Science/Research
Classifier: Topic :: Scientific/Engineering :: Bio-Informatics
Classifier: License :: OSI Approved :: MIT License
Classifier: Programming Language :: Python :: 3 :: Only
